userfolders/__init__.py
userfolders/__main__.py
userfolders/unix.py
userfolders/windows.py
userfolders-0.2.0.dist-info/LICENSE
userfolders-0.2.0.dist-info/METADATA
userfolders-0.2.0.dist-info/WHEEL
userfolders-0.2.0.dist-info/top_level.txt
userfolders-0.2.0.dist-info/RECORD
