Metadata-Version: 2.1
Name: userfolders
Version: 0.2.0
Summary: Cross-platform access to a user's special folders
Author-email: "João H. L. Corrêa" <joaohlc@duck.com>, Benjamin Johnson <bmjcode@gmail.com>
Maintainer-email: "João H. L. Corrêa" <joaohlc@duck.com>
Project-URL: Homepage, https://github.com/jhenriquelc/userpaths
Project-URL: Repository, https://github.com/jhenriquelc/userpaths.git
Project-URL: Issues, https://github.com/jhenriquelc/userpaths/issues
Keywords: documents folder,images folder,downloads folder,user folders,userpaths,winpaths,csidl,xdg,freedesktop,folders
Classifier: Development Status :: 4 - Beta
Classifier: Programming Language :: Python :: 3
Classifier: Programming Language :: Python :: 3.12
Classifier: License :: OSI Approved :: MIT License
Classifier: Operating System :: OS Independent
Requires-Python: >=3.12
License-File: LICENSE
